tests/__init__.py
tests/test_html.py
tests/test_xml.py
xq/__init__.py
xq/__main__.py
xq-0.0.4.dist-info/DESCRIPTION.rst
xq-0.0.4.dist-info/METADATA
xq-0.0.4.dist-info/RECORD
xq-0.0.4.dist-info/WHEEL
xq-0.0.4.dist-info/entry_points.txt
xq-0.0.4.dist-info/metadata.json
xq-0.0.4.dist-info/top_level.txt
