Metadata-Version: 2.0
Name: xq
Version: 0.0.4
Summary: Like jq but for XML and XPath.
Home-page: https://github.com/jeffbr13/xq
Author: Ben Jeffrey
Author-email: mail@benjeffrey.net
License: MPL 2.0
Keywords: xml xpath text
Platform: UNKNOWN
Classifier: Development Status :: 3 - Alpha
Classifier: Programming Language :: Python :: 3
Classifier: Intended Audience :: Developers
Classifier: Environment :: Console
Classifier: Topic :: Terminals
Classifier: Topic :: Text Processing :: Markup :: XML
Classifier: Topic :: Utilities
Classifier: License :: OSI Approved :: Mozilla Public License 2.0 (MPL 2.0)
Requires-Dist: lxml
Requires-Dist: pygments
